{
    "btc": {
        "bitopro": {
            "img": "static/style/img/bitopro-card-img.png",
            "percDif": -0.15,
            "price": 97917.12,
            "unitDif": -150.39,
            "url": "https://www.bitoex.com/"
        },
        "coinbase": {
            "img": "static/style/img/coinbase-card-img.png",
            "percDif": 0,
            "price": 98067.51,
            "unitDif": 0,
            "url": "https://www.coinbase.com/"
        },
        "maicoin": {
            "img": "static/style/img/maimax-card-img.png",
            "percDif": -0.01,
            "price": 98054.85,
            "unitDif": -12.66,
            "url": "https://www.maicoin.com/en"
        }
    },
    "eth": {
        "bitopro": {
            "img": "static/style/img/bitopro-card-img.png",
            "percDif": -0.15,
            "price": 3861.25,
            "unitDif": -5.93,
            "url": "https://www.bitoex.com/"
        },
        "coinbase": {
            "img": "static/style/img/coinbase-card-img.png",
            "percDif": 0,
            "price": 3867.18,
            "unitDif": 0,
            "url": "https://www.coinbase.com/"
        },
        "maicoin": {
            "img": "static/style/img/maimax-card-img.png",
            "percDif": -0.08,
            "price": 3863.91,
            "unitDif": -3.27,
            "url": "https://www.maicoin.com/en"
        }
    },
    "time": {
        "currentTime": "Dec 06 2024 11:18:16"
    }
}