{
    "btc": {
        "bitopro": {
            "img": "static/style/img/bitopro-card-img.png",
            "percDif": 0.1,
            "price": 59397.81,
            "unitDif": 61.49,
            "url": "https://www.bitoex.com/"
        },
        "coinbase": {
            "img": "static/style/img/coinbase-card-img.png",
            "percDif": 0,
            "price": 59336.32,
            "unitDif": 0,
            "url": "https://www.coinbase.com/"
        },
        "maicoin": {
            "img": "static/style/img/maimax-card-img.png",
            "percDif": -0.01,
            "price": 59328.08,
            "unitDif": -8.24,
            "url": "https://www.maicoin.com/en"
        }
    },
    "eth": {
        "bitopro": {
            "img": "static/style/img/bitopro-card-img.png",
            "percDif": 0.08,
            "price": 2593.18,
            "unitDif": 2.04,
            "url": "https://www.bitoex.com/"
        },
        "coinbase": {
            "img": "static/style/img/coinbase-card-img.png",
            "percDif": 0,
            "price": 2591.14,
            "unitDif": 0,
            "url": "https://www.coinbase.com/"
        },
        "maicoin": {
            "img": "static/style/img/maimax-card-img.png",
            "percDif": 0.04,
            "price": 2592.06,
            "unitDif": 0.92,
            "url": "https://www.maicoin.com/en"
        }
    },
    "time": {
        "currentTime": "Aug 21 2024 03:20:57"
    }
}