{
    "btc": {
        "bitopro": {
            "img": "static/style/img/bitopro-card-img.png",
            "percDif": 0.0,
            "price": 96348.53,
            "unitDif": 2.85,
            "url": "https://www.bitoex.com/"
        },
        "coinbase": {
            "img": "static/style/img/coinbase-card-img.png",
            "percDif": 0,
            "price": 96345.68,
            "unitDif": 0,
            "url": "https://www.coinbase.com/"
        },
        "maicoin": {
            "img": "static/style/img/maimax-card-img.png",
            "percDif": -0.05,
            "price": 96297.25,
            "unitDif": -48.43,
            "url": "https://www.maicoin.com/en"
        }
    },
    "eth": {
        "bitopro": {
            "img": "static/style/img/bitopro-card-img.png",
            "percDif": -0.02,
            "price": 1844.0,
            "unitDif": -0.37,
            "url": "https://www.bitoex.com/"
        },
        "coinbase": {
            "img": "static/style/img/coinbase-card-img.png",
            "percDif": 0,
            "price": 1844.37,
            "unitDif": 0,
            "url": "https://www.coinbase.com/"
        },
        "maicoin": {
            "img": "static/style/img/maimax-card-img.png",
            "percDif": -0.0,
            "price": 1844.3,
            "unitDif": -0.07,
            "url": "https://www.maicoin.com/en"
        }
    },
    "time": {
        "currentTime": "May 03 2025 21:20:00"
    }
}