{
    "btc": {
        "bitopro": {
            "img": "static/style/img/bitopro-card-img.png",
            "percDif": -1.33,
            "price": 21884.74,
            "unitDif": -294.71,
            "url": "https://www.bitoex.com/"
        },
        "coinbase": {
            "img": "static/style/img/coinbase-card-img.png",
            "percDif": 0,
            "price": 22179.45,
            "unitDif": 0,
            "url": "https://www.coinbase.com/"
        },
        "maicoin": {
            "img": "static/style/img/maimax-card-img.png",
            "percDif": -0.4,
            "price": 22091.09,
            "unitDif": -88.36,
            "url": "https://www.maicoin.com/en"
        }
    },
    "eth": {
        "bitopro": {
            "img": "static/style/img/bitopro-card-img.png",
            "percDif": -0.43,
            "price": 1536.36,
            "unitDif": -6.6,
            "url": "https://www.bitoex.com/"
        },
        "coinbase": {
            "img": "static/style/img/coinbase-card-img.png",
            "percDif": 0,
            "price": 1542.96,
            "unitDif": 0,
            "url": "https://www.coinbase.com/"
        },
        "maicoin": {
            "img": "static/style/img/maimax-card-img.png",
            "percDif": -0.43,
            "price": 1536.27,
            "unitDif": -6.69,
            "url": "https://www.maicoin.com/en"
        }
    },
    "time": {
        "currentTime": "Jul 19 2022 05:47:09"
    }
}