{
    "btc": {
        "bitopro": {
            "img": "static/style/img/bitopro-card-img.png",
            "percDif": 0.34,
            "price": 87249.96,
            "unitDif": 297.75,
            "url": "https://www.bitoex.com/"
        },
        "coinbase": {
            "img": "static/style/img/coinbase-card-img.png",
            "percDif": 0,
            "price": 86952.21,
            "unitDif": 0,
            "url": "https://www.coinbase.com/"
        },
        "maicoin": {
            "img": "static/style/img/maimax-card-img.png",
            "percDif": 0.07,
            "price": 87011.37,
            "unitDif": 59.16,
            "url": "https://www.maicoin.com/en"
        }
    },
    "eth": {
        "bitopro": {
            "img": "static/style/img/bitopro-card-img.png",
            "percDif": 0.35,
            "price": 2181.65,
            "unitDif": 7.54,
            "url": "https://www.bitoex.com/"
        },
        "coinbase": {
            "img": "static/style/img/coinbase-card-img.png",
            "percDif": 0,
            "price": 2174.11,
            "unitDif": 0,
            "url": "https://www.coinbase.com/"
        },
        "maicoin": {
            "img": "static/style/img/maimax-card-img.png",
            "percDif": 0.06,
            "price": 2175.44,
            "unitDif": 1.33,
            "url": "https://www.maicoin.com/en"
        }
    },
    "time": {
        "currentTime": "Mar 05 2025 05:21:24"
    }
}