{
    "btc": {
        "bitopro": {
            "img": "static/style/img/bitopro-card-img.png",
            "percDif": -0.04,
            "price": 94948.3,
            "unitDif": -39.29,
            "url": "https://www.bitoex.com/"
        },
        "coinbase": {
            "img": "static/style/img/coinbase-card-img.png",
            "percDif": 0,
            "price": 94987.59,
            "unitDif": 0,
            "url": "https://www.coinbase.com/"
        },
        "maicoin": {
            "img": "static/style/img/maimax-card-img.png",
            "percDif": -0.04,
            "price": 94950.17,
            "unitDif": -37.42,
            "url": "https://www.maicoin.com/en"
        }
    },
    "eth": {
        "bitopro": {
            "img": "static/style/img/bitopro-card-img.png",
            "percDif": -0.07,
            "price": 3787.92,
            "unitDif": -2.58,
            "url": "https://www.bitoex.com/"
        },
        "coinbase": {
            "img": "static/style/img/coinbase-card-img.png",
            "percDif": 0,
            "price": 3790.5,
            "unitDif": 0,
            "url": "https://www.coinbase.com/"
        },
        "maicoin": {
            "img": "static/style/img/maimax-card-img.png",
            "percDif": -0.07,
            "price": 3787.99,
            "unitDif": -2.51,
            "url": "https://www.maicoin.com/en"
        }
    },
    "time": {
        "currentTime": "Dec 04 2024 17:19:53"
    }
}