{
    "btc": {
        "bitopro": {
            "img": "static/style/img/bitopro-card-img.png",
            "percDif": -0.03,
            "price": 69956.82,
            "unitDif": -21.17,
            "url": "https://www.bitoex.com/"
        },
        "coinbase": {
            "img": "static/style/img/coinbase-card-img.png",
            "percDif": 0,
            "price": 69977.99,
            "unitDif": 0,
            "url": "https://www.coinbase.com/"
        },
        "maicoin": {
            "img": "static/style/img/maimax-card-img.png",
            "percDif": 0.03,
            "price": 70000.0,
            "unitDif": 22.01,
            "url": "https://www.maicoin.com/en"
        }
    },
    "eth": {
        "bitopro": {
            "img": "static/style/img/bitopro-card-img.png",
            "percDif": 0.04,
            "price": 2039.12,
            "unitDif": 0.82,
            "url": "https://www.bitoex.com/"
        },
        "coinbase": {
            "img": "static/style/img/coinbase-card-img.png",
            "percDif": 0,
            "price": 2038.3,
            "unitDif": 0,
            "url": "https://www.coinbase.com/"
        },
        "maicoin": {
            "img": "static/style/img/maimax-card-img.png",
            "percDif": 0.03,
            "price": 2038.88,
            "unitDif": 0.58,
            "url": "https://www.maicoin.com/en"
        }
    },
    "time": {
        "currentTime": "Mar 10 2026 21:34:01"
    }
}