{
    "btc": {
        "bitopro": {
            "img": "static/style/img/bitopro-card-img.png",
            "percDif": -0.4,
            "price": 43964.2,
            "unitDif": -177.87,
            "url": "https://www.bitoex.com/"
        },
        "coinbase": {
            "img": "static/style/img/coinbase-card-img.png",
            "percDif": 0,
            "price": 44142.07,
            "unitDif": 0,
            "url": "https://www.coinbase.com/"
        },
        "maicoin": {
            "img": "static/style/img/maimax-card-img.png",
            "percDif": -0.58,
            "price": 43888.02,
            "unitDif": -254.05,
            "url": "https://www.maicoin.com/en"
        }
    },
    "eth": {
        "bitopro": {
            "img": "static/style/img/bitopro-card-img.png",
            "percDif": -0.55,
            "price": 3119.62,
            "unitDif": -17.32,
            "url": "https://www.bitoex.com/"
        },
        "coinbase": {
            "img": "static/style/img/coinbase-card-img.png",
            "percDif": 0,
            "price": 3136.94,
            "unitDif": 0,
            "url": "https://www.coinbase.com/"
        },
        "maicoin": {
            "img": "static/style/img/maimax-card-img.png",
            "percDif": -0.54,
            "price": 3119.91,
            "unitDif": -17.03,
            "url": "https://www.maicoin.com/en"
        }
    },
    "time": {
        "currentTime": "Mar 25 2022 02:47:44"
    }
}