{
    "btc": {
        "bitopro": {
            "img": "static/style/img/bitopro-card-img.png",
            "percDif": 0.06,
            "price": 85000.0,
            "unitDif": 50.02,
            "url": "https://www.bitoex.com/"
        },
        "coinbase": {
            "img": "static/style/img/coinbase-card-img.png",
            "percDif": 0,
            "price": 84949.98,
            "unitDif": 0,
            "url": "https://www.coinbase.com/"
        },
        "maicoin": {
            "img": "static/style/img/maimax-card-img.png",
            "percDif": 0.06,
            "price": 85001.87,
            "unitDif": 51.89,
            "url": "https://www.maicoin.com/en"
        }
    },
    "eth": {
        "bitopro": {
            "img": "static/style/img/bitopro-card-img.png",
            "percDif": 0.65,
            "price": 2797.5,
            "unitDif": 18.2,
            "url": "https://www.bitoex.com/"
        },
        "coinbase": {
            "img": "static/style/img/coinbase-card-img.png",
            "percDif": 0,
            "price": 2779.3,
            "unitDif": 0,
            "url": "https://www.coinbase.com/"
        },
        "maicoin": {
            "img": "static/style/img/maimax-card-img.png",
            "percDif": 0.3,
            "price": 2787.67,
            "unitDif": 8.37,
            "url": "https://www.maicoin.com/en"
        }
    },
    "time": {
        "currentTime": "Nov 21 2025 17:21:26"
    }
}