{
    "btc": {
        "bitopro": {
            "img": "static/style/img/bitopro-card-img.png",
            "percDif": 0.12,
            "price": 70198.18,
            "unitDif": 85.52,
            "url": "https://www.bitoex.com/"
        },
        "coinbase": {
            "img": "static/style/img/coinbase-card-img.png",
            "percDif": 0,
            "price": 70112.66,
            "unitDif": 0,
            "url": "https://www.coinbase.com/"
        },
        "maicoin": {
            "img": "static/style/img/maimax-card-img.png",
            "percDif": 0.03,
            "price": 70134.05,
            "unitDif": 21.39,
            "url": "https://www.maicoin.com/en"
        }
    },
    "eth": {
        "bitopro": {
            "img": "static/style/img/bitopro-card-img.png",
            "percDif": -0.01,
            "price": 2107.98,
            "unitDif": -0.14,
            "url": "https://www.bitoex.com/"
        },
        "coinbase": {
            "img": "static/style/img/coinbase-card-img.png",
            "percDif": 0,
            "price": 2108.12,
            "unitDif": 0,
            "url": "https://www.coinbase.com/"
        },
        "maicoin": {
            "img": "static/style/img/maimax-card-img.png",
            "percDif": 0.01,
            "price": 2108.3,
            "unitDif": 0.18,
            "url": "https://www.maicoin.com/en"
        }
    },
    "time": {
        "currentTime": "Feb 10 2026 02:53:14"
    }
}